MANIFEST.in
setup.py
src/AnywhereLibrary/__init__.py
src/AnywhereLibrary/version.py
src/AnywhereLibrary/base/__init__.py
src/AnywhereLibrary/base/element.py
src/AnywhereLibrary/base/elementfinder.py
src/AnywhereLibrary/base/javascript.py
src/AnywhereLibrary/base/keywordgroup.py
src/AnywhereLibrary/base/logging.py
src/AnywhereLibrary/base/runonfailure.py
src/AnywhereLibrary/base/screenshot.py
src/AnywhereLibrary/base/util.py
src/AnywhereLibrary/base/waiting.py
src/AnywhereLibrary/cfg/configuration.xml
src/robotframework_anywherelibrary.egg-info/PKG-INFO
src/robotframework_anywherelibrary.egg-info/SOURCES.txt
src/robotframework_anywherelibrary.egg-info/dependency_links.txt
src/robotframework_anywherelibrary.egg-info/requires.txt
src/robotframework_anywherelibrary.egg-info/top_level.txt