Metadata-Version: 1.0
Name: robotframework-anywherelibrary
Version: 1.1.0
Summary: Robotframework test library for cross platform:android,ios,browser
Home-page: https://github.com/luisxiaomai/robotframework-anywherelibrary
Author: luis.lu
Author-email: luzhenyuhnr@126.com
License: UNKNOWN
Platform: any
